num2wordsnepalihindi/__init__.py
num2wordsnepalihindi/num2wordsnepalihindi.py
test/__init__.py
test/test.py
num2wordsnepalihindi-0.4.4.dist-info/LICENSE
num2wordsnepalihindi-0.4.4.dist-info/METADATA
num2wordsnepalihindi-0.4.4.dist-info/WHEEL
num2wordsnepalihindi-0.4.4.dist-info/top_level.txt
num2wordsnepalihindi-0.4.4.dist-info/RECORD
